{
    "AGE GROUP-1": {
                "STAGE-1": {
                    "Name": "No Diabetes",
                    "Urea": {"mean": 14.13, "std": 3.11},
                    "Cr": {"mean": 0.81, "std": 0.18},
                    "HbA1c": {"mean": 5.1, "std": 0.15},
                    "BGL": {"mean": 110, "std": 17},
                    "PPBG": {"mean":120, "std": 15},
                    "Chol": {"mean": 174.46, "std": 6.9},
                    "TG": {"mean": 67.8, "std": 27.4},
                    "HDL": {"mean": 59.6, "std": 19.6},
                    "LDL": {"mean": 96.4, "std": 26.8},
                    "VLDL": {"mean": 16.04, "std": 1.13},
                    "BMI": {"mean": 19.6, "std": 4.6}
                },
            
                "STAGE-2": {
                    "Name": "Pre-Diabetes",
                    "Urea": {"mean": 17.18, "std": 4.39},
                    "Cr": {"mean": 0.9, "std": 0.27},
                    "HbA1c": {"mean": 5.8, "std": 0.25},
                    "BGL": {"mean": 130, "std": 22},
                    "PPBG": {"mean":150, "std": 17.5},
                    "Chol": {"mean": 179.32, "std": 19.4},
                    "TG": {"mean": 82.9, "std": 23.1},
                    "HDL": {"mean": 55.25, "std": 20.25},
                    "LDL": {"mean": 99.4, "std": 26.8},
                    "VLDL": {"mean": 20.8, "std": 3.06},
                    "BMI": {"mean": 21.6, "std": 6.05}
                },
            
                "STAGE-3": {
                    "Name": "Diabetes",
                    "Urea": {"mean": 20.23, "std": 5.67},
                    "Cr": {"mean": 0.99, "std": 0.36},
                    "HbA1c": {"mean": 6.5, "std": 0.35},
                    "BGL": {"mean": 150, "std": 27},
                    "PPBG": {"mean":180, "std": 20},
                    "Chol": {"mean": 184.17, "std": 31.89},
                    "TG": {"mean": 98.0, "std": 28.8},
                    "HDL": {"mean": 50.9, "std": 20.9},
                    "LDL": {"mean": 102.4, "std": 26.8},
                    "VLDL": {"mean": 30, "std": 5},
                    "BMI": {"mean": 23.6, "std": 7.5}
                }
        },
    
    "AGE GROUP-2": {
                "STAGE-1": {
                    "Name": "No Diabetes",
                    "Urea": {"mean": 15, "std": 5},
                    "Cr": {"mean": 0.76, "std": 0.09},
                    "HbA1c": {"mean": 5.25, "std": 0.48},
                    "BGL": {"mean": 92.79, "std": 11.53},
                    "PPBG": {"mean":125, "std": 20},
                    "Chol": {"mean": 104, "std": 19.99},
                    "TG": {"mean": 80.6, "std": 25.2},
                    "HDL": {"mean": 55.2, "std": 19.6},
                    "LDL": {"mean": 100.2, "std": 29},
                    "VLDL": {"mean": 16.04, "std": 1.13},
                    "BMI": {"mean": 21.4, "std": 5.1}
                },
            
                "STAGE-2": {
                    "Name": "Pre-Diabetes",
                    "Urea": {"mean": 17.87, "std": 3.62},
                    "Cr": {"mean": 0.98, "std": 0.15},
                    "HbA1c": {"mean": 6.31, "std": 1.18},
                    "BGL": {"mean": 117.38, "std": 39.72},
                    "PPBG": {"mean":162.5, "std": 22.5},
                    "Chol": {"mean": 102.0, "std": 20.34},
                    "TG": {"mean": 87.45, "std": 29.85},
                    "HDL": {"mean": 51.75, "std": 20.3},
                    "LDL": {"mean": 105.5, "std": 31.4},
                    "VLDL": {"mean": 20.8, "std": 3.06},
                    "BMI": {"mean": 23.65, "std": 6.6}
                },
                
                "STAGE-3": {
                    "Name": "Diabetes",
                    "Urea": {"mean": 20.74, "std": 2.25},
                    "Cr": {"mean": 1.2, "std": 0.2},
                    "HbA1c": {"mean": 7.37, "std": 1.89},
                    "BGL": {"mean": 141.98, "std": 67.92},
                    "PPBG": {"mean":200, "std": 25},
                    "Chol": {"mean": 100, "std": 20.7},
                    "TG": {"mean": 94.3, "std": 24.5},
                    "HDL": {"mean": 48.3, "std": 21},
                    "LDL": {"mean": 110.8, "std": 33.8},
                    "VLDL": {"mean": 30, "std": 5},
                    "BMI": {"mean": 25.9, "std": 8.1}
                }
        },
        
    "AGE GROUP-3": {
                "STAGE-1": {
                    "Name": "No Diabetes",
                    "Urea": {"mean": 18.31, "std": 4.55},
                    "Cr": {"mean": 0.89, "std": 0.21},
                    "HbA1c": {"mean": 5.4, "std": 0.2},
                    "BGL": {"mean": 100, "std": 15},
                    "PPBG": {"mean":130, "std": 25},
                    "Chol": {"mean": 197.24, "std": 31.44},
                    "TG": {"mean": 122.78, "std": 41.55},
                    "HDL": {"mean": 52.8, "std": 12.84},
                    "LDL": {"mean": 107.5, "std": 27.48},
                    "VLDL": {"mean": 16.04, "std": 1.13},
                    "BMI": {"mean": 23.39, "std": 2.59}
                },
            
                "STAGE-2": {
                    "Name": "Pre-Diabetes",
                    "Urea": {"mean": 23.76, "std": 7.44},
                    "Cr": {"mean": 1.01, "std": 0.49},
                    "HbA1c": {"mean": 6.15, "std": 0.4},
                    "BGL": {"mean": 125.0, "std": 20.0},
                    "PPBG": {"mean":175, "std": 27.5},
                    "Chol": {"mean": 188.52, "std": 32.07},
                    "TG": {"mean": 139.33, "std": 49.15},
                    "HDL": {"mean": 50.28, "std": 12.88},
                    "LDL": {"mean": 110.43, "std": 29.59},
                    "VLDL": {"mean": 20.8, "std": 3.06},
                    "BMI": {"mean": 24.24, "std": 2.71}
                },
            
                "STAGE-3": {
                    "Name": "Diabetes",
                    "Urea": {"mean": 29.22, "std": 10.32},
                    "Cr": {"mean": 1.13, "std": 0.47},
                    "HbA1c": {"mean": 6.9, "std": 0.6},
                    "BGL": {"mean": 150, "std": 25},
                    "PPBG": {"mean":220, "std": 30},
                    "Chol": {"mean": 179.81, "std": 32.7},
                    "TG": {"mean": 155.89, "std": 76.75},
                    "HDL": {"mean": 47.76, "std": 12.93},
                    "LDL": {"mean": 116.1, "std": 31.7},
                    "VLDL": {"mean": 30, "std": 5},
                    "BMI": {"mean": 25.09, "std": 2.83}
                }
        }
    
}
